.gitignore
.pylintrc
LICENSE
MANIFEST.in
README.md
requirements.txt
setup.py
.idea/res-service-core.iml
debian/changelog
debian/compat
debian/control
debian/copyright
debian/postinst
debian/rules
res/__init__.py
res/core/__init__.py
res/core/argument_parser.py
res/core/child_process_protocol.py
res/core/configuration.py
res/core/logger.py
res/core/systemd_watchdog.py
res/core/utils.py
res_core.egg-info/PKG-INFO
res_core.egg-info/SOURCES.txt
res_core.egg-info/dependency_links.txt
res_core.egg-info/requires.txt
res_core.egg-info/top_level.txt