Metadata-Version: 1.1
Name: res-core
Version: 1.0.2
Summary: Resystem common service package
Home-page: https://github.com/AngryDevelopersLLC/res-core
Author: Vadim Markovtsev
Author-email: gmarkhor@gmail.com
License: New BSD
Download-URL: https://github.com/AngryDevelopersLLC/res-core
Platform: UNKNOWN
Classifier: Development Status :: 5 - Production/Stable
Classifier: Environment :: Console
Classifier: Intended Audience :: Developers
Classifier: License :: OSI Approved :: BSD License
Classifier: Operating System :: POSIX
Classifier: Programming Language :: Python :: 3.4
Classifier: Programming Language :: Python :: 3.5
Classifier: Topic :: Software Development :: Libraries
